[
  {
    "package": "sendgridr",
    "url": "https://github.com/mrchypark/sendgridr"
  },
  {
    "package": "elbird",
    "url": "https://github.com/mrchypark/elbird"
  },
  {
    "package": "josaplay",
    "url": "https://github.com/mrchypark/josaplay"
  },
  {
    "package": "multilinguer",
    "url": "https://github.com/mrchypark/multilinguer"
  },
  {
    "package": "stdictkr",
    "url": "https://github.com/mrchypark/stdictkr"
  },
   {
    "package": "tqk",
    "url": "https://github.com/mrchypark/tqk"
  }
]
